{
  "img": "modules/dcc-core-book/assets/svg/game-icons-net/up-card.svg",
  "system": {
    "class": "dwarf-sapper",
    "level": "5",
    "levelData": "system.details.attackBonus=+4\nsystem.attributes.critical.die=1d20\nsystem.attributes.critical.table=II\nsystem.attributes.actionDice.value=1d20,1d14\nsystem.attributes.hitDice.value=1d8\nsystem.class.luckDie=d4\nsystem.class.backstab=+8\nsystem.skills.sneakSilently.value=+8\nsystem.skills.hideInShadows.value=+8\nsystem.skills.pickLock.value=+4\nsystem.skills.findTrap.value=+9\nsystem.skills.disableTrap.value=+9\nsystem.saves.ref.classBonus=+3\nsystem.saves.frt.classBonus=+2\nsystem.saves.wil.classBonus=+2\n"
  },
  "name": "dwarf-sapper-5",
  "type": "level",
  "folder": "GJlVBMl5aWUL7mhR",
  "_id": "P40U2USAzf2duhv2",
  "effects": [],
  "sort": 500,
  "ownership": {
    "default": 0
  },
  "flags": {},
  "_stats": {
    "compendiumSource": null,
    "duplicateSource": null,
    "exportSource": null,
    "coreVersion": "13.348",
    "systemId": "dcc",
    "systemVersion": "0.70.0",
    "createdTime": 0,
    "modifiedTime": 0,
    "lastModifiedBy": "dccGongfarmer000"
  },
  "_key": "!items!P40U2USAzf2duhv2"
}
